topsis/102003395.py
topsis/__init.py
Topsis_Sidharth_102003395-0.1.dist-info/LICENSE.txt
Topsis_Sidharth_102003395-0.1.dist-info/METADATA
Topsis_Sidharth_102003395-0.1.dist-info/WHEEL
Topsis_Sidharth_102003395-0.1.dist-info/entry_points.txt
Topsis_Sidharth_102003395-0.1.dist-info/top_level.txt
Topsis_Sidharth_102003395-0.1.dist-info/RECORD
