Metadata-Version: 2.1
Name: Topsis-Sidharth-102003395
Version: 0.1
Summary: Implements topsis on the given input data file and generates topsis score and ranks accordingly.
Home-page: https://github.com/hsurap/Topsis-Sidharth-102003404
Author: S Sidharth
Author-email: ssidharth_be20@thapar.edu
License: MIT
Classifier: License :: OSI Approved :: MIT License
Classifier: Programming Language :: Python :: 3.8
Classifier: Programming Language :: Python :: 3.9
Classifier: Programming Language :: Python :: 3.10
License-File: LICENSE.txt
Requires-Dist: pandas
